pyderive/__init__.py
pyderive/abc.py
pyderive/compat.py
pyderive/compile.py
pyderive/dataclasses.py
pyderive/parse.py
pyderive/py.typed
pyderive/extensions/__init__.py
pyderive/extensions/utils.py
pyderive/extensions/serde/__init__.py
pyderive/extensions/serde/impl.py
pyderive/extensions/serde/serde.py
pyderive/extensions/serde/xml.py
pyderive/extensions/validate/__init__.py
pyderive/extensions/validate/generic.py
pyderive/extensions/validate/helpers.py
pyderive/extensions/validate/types.py
pyderive/extensions/validate/validators.py
pyderive/tests/__init__.py
pyderive/tests/dataclasses.py
pyderive/tests/extensions/__init__.py
pyderive/tests/extensions/serde.py
pyderive/tests/extensions/validate.py
pyderive3-0.0.8.dist-info/LICENSE
pyderive3-0.0.8.dist-info/METADATA
pyderive3-0.0.8.dist-info/WHEEL
pyderive3-0.0.8.dist-info/top_level.txt
pyderive3-0.0.8.dist-info/RECORD
