Metadata-Version: 2.1
Name: pyderive3
Version: 0.0.8
Summary: Python3 Custom Dataclass Helpers
Author-email: Andrew C Scott <imgurbot12@gmail.com>
License: The MIT License (MIT)
Project-URL: Repository, https://github.com/imgurbot12/pyderive
Keywords: dataclass,custom,builder,validation,serialization
Classifier: Intended Audience :: Developers
Classifier: License :: OSI Approved :: MIT License
Classifier: Programming Language :: Python :: 3
Classifier: Programming Language :: Python :: 3.8
Classifier: Programming Language :: Python :: 3.9
Classifier: Programming Language :: Python :: 3.10
Classifier: Programming Language :: Python :: 3.11
Classifier: Programming Language :: Python :: 3.12
Requires-Python: >=3.8
License-File: LICENSE
Requires-Dist: typing-extensions>=4.7.1
